EmailAdapter/Core.py
EmailAdapter/__init__.py
erispulse_emailadapter-1.1.0.dist-info/licenses/LICENSE
erispulse_emailadapter-1.1.0.dist-info/METADATA
erispulse_emailadapter-1.1.0.dist-info/WHEEL
erispulse_emailadapter-1.1.0.dist-info/entry_points.txt
erispulse_emailadapter-1.1.0.dist-info/top_level.txt
erispulse_emailadapter-1.1.0.dist-info/RECORD
