Metadata-Version: 2.4
Name: ErisPulse-EmailAdapter
Version: 1.1.0
Summary: ErisPulse邮箱适配器，支持多账号管理、HTML内容和附件发送
Author-email: wsu2059q <wsu2059@qq.com>
Project-URL: homepage, https://github.com/ErisPulse/ErisPulse-EmailAdapter
License-File: LICENSE
Dynamic: license-file
